threatbus_cif3/__init__.py
threatbus_cif3/message_mapping.py
threatbus_cif3/plugin.py
threatbus_cif3-2022.5.16.dist-info/METADATA
threatbus_cif3-2022.5.16.dist-info/WHEEL
threatbus_cif3-2022.5.16.dist-info/entry_points.txt
threatbus_cif3-2022.5.16.dist-info/top_level.txt
threatbus_cif3-2022.5.16.dist-info/RECORD
