Metadata-Version: 2.1
Name: threatbus-cif3
Version: 2022.5.16
Summary: A plugin to enable indicators to be submitted to CIFv3 in real-time
Home-page: https://github.com/tenzir/threatbus
Author: Michael Davis, derived from work by Tenzir
Author-email: 
License: BSD 3-clause
Keywords: cif,cifv3,cif3,renisac,ren-isac,threatbus,Threat Bus,threat intelligence,TI,TI dissemination
Platform: UNKNOWN
Classifier: Development Status :: 3 - Alpha
Classifier: Environment :: Plugins
Classifier: License :: OSI Approved :: BSD License
Classifier: Operating System :: MacOS :: MacOS X
Classifier: Operating System :: POSIX :: Linux
Classifier: Programming Language :: Python :: 3
Classifier: Topic :: Scientific/Engineering :: Information Analysis
Classifier: Topic :: Scientific/Engineering :: Interface Engine/Protocol Translator
Classifier: Topic :: Security
Classifier: Topic :: Software Development :: Object Brokering
Classifier: Topic :: System :: Distributed Computing
Requires-Python: >=3.6
Requires-Dist: stix2 (>=3.0)
Requires-Dist: threatbus (>=2022.5.16)
Requires-Dist: cifsdk (<4.0,>3.0.0rc4)
